{"BTCUSDT": {"sym": "BTCUSDT", "sl": 0, "ss": 0, "oh_score": 0, "od_score": 0, "rsi1h": 28.3, "rsi5m": 42.0, "fund": -0.0019, "cvd": 0.0, "oi": 0.0, "long_pct": 68, "trend": "bearish", "ms4h": "neutral", "ms1h": "neutral", "block_long": false, "block_short": false, "btc_chg": -0.19, "final_direction": null, "final_score": 0, "price": 62357.9, "price_chg_1h": -0.19, "sq_score": 0, "ml_score": 0, "vol_24h": 11458786726.74}, "ETHUSDT": {"sym": "ETHUSDT", "sl": 0, "ss": 0, "oh_score": 0, "od_score": 3, "rsi1h": 26.3, "rsi5m": 45.6, "fund": -0.0039, "cvd": 0.0, "oi": 0.0, "long_pct": 72, "trend": "bearish", "ms4h": "neutral", "ms1h": "bearish", "block_long": false, "block_short": false, "btc_chg": -0.19, "final_direction": null, "final_score": 3, "price": 1659.27, "price_chg_1h": -0.04, "sq_score": 0, "ml_score": 0, "vol_24h": 7753928051.49}, "SPCXUSDT": {"sym": "SPCXUSDT", "sl": 0, "ss": 0, "oh_score": 0, "od_score": 0, "rsi1h": 39.0, "rsi5m": 49.4, "fund": 0.0504, "cvd": -13.2, "oi": 0.0, "long_pct": 80, "trend": "bearish", "ms4h": "bearish", "ms1h": "bullish", "block_long": false, "block_short": false, "btc_chg": -0.19, "final_direction": null, "final_score": 0, "price": 159.19, "price_chg_1h": 2.57, "sq_score": 0, "ml_score": 0, "vol_24h": 3764566346.0506}, "SOLUSDT": {"sym": "SOLUSDT", "sl": 0, "ss": 0, "oh_score": 0, "od_score": 3, "rsi1h": 27.8, "rsi5m": 47.1, "fund": -0.0209, "cvd": 0.0, "oi": 0.0, "long_pct": 76, "trend": "neutral", "ms4h": "neutral", "ms1h": "neutral", "block_long": false, "block_short": false, "btc_chg": -0.19, "final_direction": null, "final_score": 3, "price": 68.82, "price_chg_1h": -0.62, "sq_score": 0, "ml_score": 0, "vol_24h": 1758620131.3971}, "SNDKUSDT": {"sym": "SNDKUSDT", "sl": 0, "ss": 0, "oh_score": 0, "od_score": 0, "rsi1h": 29.9, "rsi5m": 45.3, "fund": 0.0711, "cvd": -77.0, "oi": 0.0, "long_pct": 59, "trend": "neutral", "ms4h": "neutral", "ms1h": "neutral", "block_long": false, "block_short": false, "btc_chg": -0.19, "final_direction": null, "final_score": 0, "price": 1978.23, "price_chg_1h": -5.71, "sq_score": 0, "ml_score": 0, "vol_24h": 1258703607.3709}, "HYPEUSDT": {"sym": "HYPEUSDT", "sl": 0, "ss": 0, "oh_score": 0, "od_score": 1, "rsi1h": 30.0, "rsi5m": 47.1, "fund": 0.005, "cvd": 6.2, "oi": 0.0, "long_pct": 56, "trend": "bearish", "ms4h": "neutral", "ms1h": "bearish", "block_long": false, "block_short": false, "btc_chg": -0.19, "final_direction": null, "final_score": 1, "price": 62.165, "price_chg_1h": -1.72, "sq_score": 0, "ml_score": 0, "vol_24h": 968611109.34652}, "ZECUSDT": {"sym": "ZECUSDT", "sl": 0, "ss": 0, "oh_score": 0, "od_score": 0, "rsi1h": 32.3, "rsi5m": 48.2, "fund": -0.0118, "cvd": -61.8, "oi": 0.0, "long_pct": 42, "trend": "bearish", "ms4h": "bearish", "ms1h": "neutral", "block_long": false, "block_short": false, "btc_chg": -0.19, "final_direction": null, "final_score": 0, "price": 415.59, "price_chg_1h": -2.11, "sq_score": 0, "ml_score": 0, "vol_24h": 630367590.84}, "XRPUSDT": {"sym": "XRPUSDT", "sl": 0, "ss": 0, "oh_score": 0, "od_score": 0, "rsi1h": 34.9, "rsi5m": 45.0, "fund": -0.0079, "cvd": 0.0, "oi": 0.0, "long_pct": 72, "trend": "bearish", "ms4h": "neutral", "ms1h": "bearish", "block_long": false, "block_short": false, "btc_chg": -0.19, "final_direction": null, "final_score": 0, "price": 1.0987, "price_chg_1h": -0.91, "sq_score": 0, "ml_score": 0, "vol_24h": 548866779.8417}, "WLDUSDT": {"sym": "WLDUSDT", "sl": 0, "ss": 0, "oh_score": 0, "od_score": 0, "rsi1h": 32.1, "rsi5m": 52.0, "fund": 0.0014, "cvd": -45.6, "oi": 0.0, "long_pct": 50, "trend": "bearish", "ms4h": "bearish", "ms1h": "bearish", "block_long": true, "block_short": false, "btc_chg": -0.19, "final_direction": null, "final_score": 0, "price": 0.5412, "price_chg_1h": -5.24, "sq_score": 0, "ml_score": 0, "vol_24h": 409388203.3551}, "REUSDT": {"sym": "REUSDT", "sl": 0, "ss": 0, "oh_score": 0, "od_score": 0, "rsi1h": 43.3, "rsi5m": 53.3, "fund": -0.2417, "cvd": 64.2, "oi": 0.0, "long_pct": 41, "trend": "bearish", "ms4h": "bearish", "ms1h": "bearish", "block_long": true, "block_short": false, "btc_chg": -0.19, "final_direction": null, "final_score": 0, "price": 0.8376, "price_chg_1h": 4.1, "sq_score": 0, "ml_score": 0, "vol_24h": 363741297.7348}, "MRVLUSDT": {"sym": "MRVLUSDT", "sl": 0, "ss": 0, "oh_score": 0, "od_score": 0, "rsi1h": 24.8, "rsi5m": 42.0, "fund": 0.0146, "cvd": -10.2, "oi": 0.0, "long_pct": 84, "trend": "bearish", "ms4h": "neutral", "ms1h": "neutral", "block_long": false, "block_short": false, "btc_chg": -0.19, "final_direction": null, "final_score": 0, "price": 279.65, "price_chg_1h": -1.85, "sq_score": 0, "ml_score": 0, "vol_24h": 342938946.0609}, "DOGEUSDT": {"sym": "DOGEUSDT", "sl": 0, "ss": 0, "oh_score": 0, "od_score": 2, "rsi1h": 28.5, "rsi5m": 49.8, "fund": -0.0033, "cvd": 0.0, "oi": 0.0, "long_pct": 70, "trend": "bearish", "ms4h": "neutral", "ms1h": "bearish", "block_long": false, "block_short": false, "btc_chg": -0.19, "final_direction": null, "final_score": 2, "price": 0.07842, "price_chg_1h": -1.4, "sq_score": 0, "ml_score": 0, "vol_24h": 341992703.88236}, "DRAMUSDT": {"sym": "DRAMUSDT", "sl": 0, "ss": 0, "oh_score": 0, "od_score": 0, "rsi1h": 29.0, "rsi5m": 42.2, "fund": 0.0511, "cvd": -20.0, "oi": 0.0, "long_pct": 82, "trend": "neutral", "ms4h": "neutral", "ms1h": "neutral", "block_long": false, "block_short": false, "btc_chg": -0.19, "final_direction": null, "final_score": 0, "price": 69.91, "price_chg_1h": -2.65, "sq_score": 0, "ml_score": 0, "vol_24h": 333590440.5912}, "BNBUSDT": {"sym": "BNBUSDT", "sl": 0, "ss": 0, "oh_score": 0, "od_score": 3, "rsi1h": 29.2, "rsi5m": 54.5, "fund": 0.0, "cvd": 0.0, "oi": 0.0, "long_pct": 76, "trend": "bearish", "ms4h": "neutral", "ms1h": "neutral", "block_long": false, "block_short": false, "btc_chg": -0.19, "final_direction": null, "final_score": 3, "price": 574.83, "price_chg_1h": 0.14, "sq_score": 0, "ml_score": 0, "vol_24h": 287218417.768}, "LABUSDT": {"sym": "LABUSDT", "sl": 0, "ss": 0, "oh_score": 0, "od_score": 0, "rsi1h": 48.2, "rsi5m": 46.6, "fund": -0.2546, "cvd": -91.4, "oi": 0.0, "long_pct": 34, "trend": "bullish", "ms4h": "neutral", "ms1h": "bearish", "block_long": false, "block_short": false, "btc_chg": -0.19, "final_direction": null, "final_score": 0, "price": 15.154, "price_chg_1h": -6.22, "sq_score": 0, "ml_score": 0, "vol_24h": 268136987.22604}, "NEARUSDT": {"sym": "NEARUSDT", "sl": 0, "ss": 0, "oh_score": 0, "od_score": 0, "rsi1h": 34.8, "rsi5m": 47.2, "fund": 0.0073, "cvd": -37.4, "oi": 0.0, "long_pct": 47, "trend": "bearish", "ms4h": "bearish", "ms1h": "neutral", "block_long": false, "block_short": false, "btc_chg": -0.19, "final_direction": null, "final_score": 0, "price": 1.984, "price_chg_1h": -1.29, "sq_score": 0, "ml_score": 0, "vol_24h": 169727961.737}, "ADAUSDT": {"sym": "ADAUSDT", "sl": 0, "ss": 0, "oh_score": 0, "od_score": 0, "rsi1h": 29.4, "rsi5m": 31.3, "fund": -0.0123, "cvd": -8.4, "oi": 0.0, "long_pct": 68, "trend": "bearish", "ms4h": "bearish", "ms1h": "bearish", "block_long": true, "block_short": false, "btc_chg": -0.19, "final_direction": null, "final_score": 0, "price": 0.1502, "price_chg_1h": -2.15, "sq_score": 0, "ml_score": 0, "vol_24h": 162848964.4085}, "TAOUSDT": {"sym": "TAOUSDT", "sl": 0, "ss": 0, "oh_score": 0, "od_score": 0, "rsi1h": 33.6, "rsi5m": 46.3, "fund": 0.005, "cvd": -90.0, "oi": 0.0, "long_pct": 53, "trend": "bearish", "ms4h": "bearish", "ms1h": "bearish", "block_long": true, "block_short": false, "btc_chg": -0.19, "final_direction": null, "final_score": 0, "price": 216.27, "price_chg_1h": -2.22, "sq_score": 0, "ml_score": 0, "vol_24h": 133700886.59}, "CRCLUSDT": {"sym": "CRCLUSDT", "sl": 0, "ss": 0, "oh_score": 0, "od_score": 0, "rsi1h": 34.7, "rsi5m": 41.8, "fund": 0.0001, "cvd": 19.6, "oi": 0.0, "long_pct": 78, "trend": "bearish", "ms4h": "neutral", "ms1h": "neutral", "block_long": false, "block_short": false, "btc_chg": -0.19, "final_direction": null, "final_score": 0, "price": 75.7, "price_chg_1h": -2.15, "sq_score": 0, "ml_score": 0, "vol_24h": 125995909.6758}, "BICOUSDT": {"sym": "BICOUSDT", "sl": 0, "ss": 0, "oh_score": 0, "od_score": 0, "rsi1h": 30.1, "rsi5m": 31.3, "fund": -0.0193, "cvd": 66.4, "oi": 0.0, "long_pct": 53, "trend": "neutral", "ms4h": "bearish", "ms1h": "neutral", "block_long": false, "block_short": false, "btc_chg": -0.19, "final_direction": null, "final_score": 0, "price": 0.02711, "price_chg_1h": 0.74, "sq_score": 0, "ml_score": 0, "vol_24h": 119377831.03134}, "AVAXUSDT": {"sym": "AVAXUSDT", "sl": 0, "ss": 0, "oh_score": 0, "od_score": 0, "rsi1h": 54.9, "rsi5m": 68.4, "fund": 0.002, "cvd": -41.8, "oi": 0.0, "long_pct": 63, "trend": "neutral", "ms4h": "bearish", "ms1h": "neutral", "block_long": false, "block_short": false, "btc_chg": -0.19, "final_direction": null, "final_score": 0, "price": 6.335, "price_chg_1h": 1.3, "sq_score": 0, "ml_score": 0, "vol_24h": 118811954.243}, "FOLKSUSDT": {"sym": "FOLKSUSDT", "sl": 0, "ss": 0, "oh_score": 0, "od_score": 0, "rsi1h": 56.2, "rsi5m": 43.3, "fund": 0.005, "cvd": 69.2, "oi": 0.0, "long_pct": 66, "trend": "neutral", "ms4h": "neutral", "ms1h": "neutral", "block_long": false, "block_short": false, "btc_chg": -0.19, "final_direction": null, "final_score": 0, "price": 2.531, "price_chg_1h": -1.71, "sq_score": 0, "ml_score": 0, "vol_24h": 117947647.6641}, "LINKUSDT": {"sym": "LINKUSDT", "sl": 0, "ss": 0, "oh_score": 0, "od_score": 1, "rsi1h": 31.7, "rsi5m": 51.9, "fund": -0.0039, "cvd": 0.0, "oi": 0.0, "long_pct": 63, "trend": "bearish", "ms4h": "neutral", "ms1h": "bearish", "block_long": false, "block_short": false, "btc_chg": -0.19, "final_direction": null, "final_score": 1, "price": 7.573, "price_chg_1h": -0.5, "sq_score": 0, "ml_score": 0, "vol_24h": 112805362.364}, "ENAUSDT": {"sym": "ENAUSDT", "sl": 0, "ss": 0, "oh_score": 0, "od_score": 0, "rsi1h": 32.2, "rsi5m": 47.1, "fund": -0.0028, "cvd": 0.0, "oi": 0.0, "long_pct": 65, "trend": "neutral", "ms4h": "neutral", "ms1h": "bearish", "block_long": false, "block_short": false, "btc_chg": -0.19, "final_direction": null, "final_score": 0, "price": 0.08585, "price_chg_1h": -0.27, "sq_score": 0, "ml_score": 0, "vol_24h": 109310335.50153}, "BTWUSDT": {"sym": "BTWUSDT", "sl": 0, "ss": 0, "oh_score": 0, "od_score": 0, "rsi1h": 58.5, "rsi5m": 60.7, "fund": 0.0757, "cvd": 33.0, "oi": 0.0, "long_pct": 55, "trend": "bullish", "ms4h": "neutral", "ms1h": "neutral", "block_long": false, "block_short": false, "btc_chg": -0.19, "final_direction": null, "final_score": 0, "price": 0.10043, "price_chg_1h": -2.83, "sq_score": 0, "ml_score": 0, "vol_24h": 108816768.157548}, "LAYERUSDT": {"sym": "LAYERUSDT", "sl": 0, "ss": 0, "oh_score": 0, "od_score": 0, "rsi1h": 48.8, "rsi5m": 33.5, "fund": -0.164, "cvd": -4.6, "oi": 0.0, "long_pct": 61, "trend": "bullish", "ms4h": "neutral", "ms1h": "bearish", "block_long": false, "block_short": false, "btc_chg": -0.19, "final_direction": null, "final_score": 0, "price": 0.07099, "price_chg_1h": -8.49, "sq_score": 0, "ml_score": 0, "vol_24h": 97092605.713377}, "BCHUSDT": {"sym": "BCHUSDT", "sl": 0, "ss": 0, "oh_score": 0, "od_score": 0, "rsi1h": 37.3, "rsi5m": 56.2, "fund": 0.0056, "cvd": 0.0, "oi": 0.0, "long_pct": 59, "trend": "bearish", "ms4h": "neutral", "ms1h": "neutral", "block_long": false, "block_short": false, "btc_chg": -0.19, "final_direction": null, "final_score": 0, "price": 191.23, "price_chg_1h": 0.09, "sq_score": 0, "ml_score": 0, "vol_24h": 96692215.63}, "CBRSUSDT": {"sym": "CBRSUSDT", "sl": 0, "ss": 0, "oh_score": 0, "od_score": 0, "rsi1h": 36.4, "rsi5m": 42.2, "fund": 0.0, "cvd": 36.2, "oi": 0.0, "long_pct": 69, "trend": "neutral", "ms4h": "neutral", "ms1h": "neutral", "block_long": false, "block_short": false, "btc_chg": -0.19, "final_direction": null, "final_score": 0, "price": 234.57, "price_chg_1h": 7.72, "sq_score": 0, "ml_score": 0, "vol_24h": 92382863.0196}, "IDUSDT": {"sym": "IDUSDT", "sl": 0, "ss": 0, "oh_score": 0, "od_score": 0, "rsi1h": 41.5, "rsi5m": 41.7, "fund": -0.069, "cvd": -65.2, "oi": 0.0, "long_pct": 55, "trend": "neutral", "ms4h": "neutral", "ms1h": "neutral", "block_long": false, "block_short": false, "btc_chg": -0.19, "final_direction": null, "final_score": 0, "price": 0.03381, "price_chg_1h": -1.49, "sq_score": 0, "ml_score": 0, "vol_24h": 90554902.89371}, "XLMUSDT": {"sym": "XLMUSDT", "sl": 0, "ss": 0, "oh_score": 0, "od_score": 0, "rsi1h": 28.7, "rsi5m": 46.3, "fund": 0.0005, "cvd": 0.0, "oi": 0.0, "long_pct": 46, "trend": "bearish", "ms4h": "bearish", "ms1h": "bearish", "block_long": true, "block_short": false, "btc_chg": -0.19, "final_direction": null, "final_score": 0, "price": 0.19443, "price_chg_1h": 0.38, "sq_score": 0, "ml_score": 0, "vol_24h": 87750278.35244}, "KORUUSDT": {"sym": "KORUUSDT", "sl": 0, "ss": 0, "oh_score": 0, "od_score": 0, "rsi1h": 16.2, "rsi5m": 46.1, "fund": 0.3756, "cvd": 7.0, "oi": 0.0, "long_pct": 69, "trend": "neutral", "ms4h": "neutral", "ms1h": "bearish", "block_long": false, "block_short": false, "btc_chg": -0.19, "final_direction": null, "final_score": 0, "price": 734.22, "price_chg_1h": -3.81, "sq_score": 0, "ml_score": 0, "vol_24h": 85494717.4922}, "BZUSDT": {"sym": "BZUSDT", "sl": 0, "ss": 0, "oh_score": 0, "od_score": 0, "rsi1h": 39.9, "rsi5m": 39.5, "fund": 0.0, "cvd": 0.0, "oi": 0.0, "long_pct": 73, "trend": "bearish", "ms4h": "bearish", "ms1h": "neutral", "block_long": false, "block_short": false, "btc_chg": -0.19, "final_direction": null, "final_score": 0, "price": 76.97, "price_chg_1h": -0.59, "sq_score": 0, "ml_score": 0, "vol_24h": 83213522.6574}, "FILUSDT": {"sym": "FILUSDT", "sl": 0, "ss": 0, "oh_score": 0, "od_score": 0, "rsi1h": 34.0, "rsi5m": 52.1, "fund": -0.0022, "cvd": -38.8, "oi": 0.0, "long_pct": 58, "trend": "bearish", "ms4h": "bearish", "ms1h": "bearish", "block_long": true, "block_short": false, "btc_chg": -0.19, "final_direction": null, "final_score": 0, "price": 0.776, "price_chg_1h": 2.51, "sq_score": 0, "ml_score": 0, "vol_24h": 76288025.521}, "HUSDT": {"sym": "HUSDT", "sl": 0, "ss": 0, "oh_score": 0, "od_score": 0, "rsi1h": 37.2, "rsi5m": 49.3, "fund": 0.005, "cvd": -30.0, "oi": 0.0, "long_pct": 61, "trend": "bearish", "ms4h": "bearish", "ms1h": "bearish", "block_long": true, "block_short": false, "btc_chg": -0.19, "final_direction": null, "final_score": 0, "price": 0.09897, "price_chg_1h": -18.15, "sq_score": 0, "ml_score": 0, "vol_24h": 72316273.89439}, "UNIUSDT": {"sym": "UNIUSDT", "sl": 0, "ss": 0, "oh_score": 0, "od_score": 0, "rsi1h": 39.2, "rsi5m": 64.7, "fund": 0.0084, "cvd": 0.0, "oi": 0.0, "long_pct": 60, "trend": "bearish", "ms4h": "neutral", "ms1h": "bearish", "block_long": false, "block_short": false, "btc_chg": -0.19, "final_direction": null, "final_score": 0, "price": 2.894, "price_chg_1h": 0.17, "sq_score": 0, "ml_score": 0, "vol_24h": 69465495.371}, "LTCUSDT": {"sym": "LTCUSDT", "sl": 0, "ss": 0, "oh_score": 0, "od_score": 0, "rsi1h": 27.2, "rsi5m": 37.3, "fund": -0.0035, "cvd": -12.0, "oi": 0.0, "long_pct": 70, "trend": "bearish", "ms4h": "neutral", "ms1h": "bearish", "block_long": false, "block_short": false, "btc_chg": -0.19, "final_direction": null, "final_score": 0, "price": 41.99, "price_chg_1h": -3.36, "sq_score": 0, "ml_score": 0, "vol_24h": 66110155.24}, "AAVEUSDT": {"sym": "AAVEUSDT", "sl": 0, "ss": 0, "oh_score": 0, "od_score": 0, "rsi1h": 38.6, "rsi5m": 48.3, "fund": 0.0085, "cvd": 0.0, "oi": 0.0, "long_pct": 63, "trend": "neutral", "ms4h": "bearish", "ms1h": "bearish", "block_long": true, "block_short": false, "btc_chg": -0.19, "final_direction": null, "final_score": 0, "price": 71.98, "price_chg_1h": -1.06, "sq_score": 0, "ml_score": 0, "vol_24h": 66552951.204}, "TRUMPUSDT": {"sym": "TRUMPUSDT", "sl": 0, "ss": 0, "oh_score": 0, "od_score": 0, "rsi1h": 30.0, "rsi5m": 54.0, "fund": -0.0088, "cvd": 0.0, "oi": 0.0, "long_pct": 63, "trend": "bearish", "ms4h": "bearish", "ms1h": "bearish", "block_long": true, "block_short": false, "btc_chg": -0.19, "final_direction": null, "final_score": 0, "price": 1.758, "price_chg_1h": 0.57, "sq_score": 0, "ml_score": 0, "vol_24h": 64939229.7428}, "NBISUSDT": {"sym": "NBISUSDT", "sl": 0, "ss": 0, "oh_score": 0, "od_score": 0, "rsi1h": 30.1, "rsi5m": 41.5, "fund": 0.0, "cvd": -11.0, "oi": 0.0, "long_pct": 70, "trend": "neutral", "ms4h": "neutral", "ms1h": "bullish", "block_long": false, "block_short": false, "btc_chg": -0.19, "final_direction": null, "final_score": 0, "price": 276.45, "price_chg_1h": 5.14, "sq_score": 0, "ml_score": 0, "vol_24h": 59947299.621}, "ONDOUSDT": {"sym": "ONDOUSDT", "sl": 0, "ss": 0, "oh_score": 0, "od_score": 0, "rsi1h": 25.4, "rsi5m": 40.2, "fund": 0.0003, "cvd": 0.0, "oi": 0.0, "long_pct": 46, "trend": "bearish", "ms4h": "neutral", "ms1h": "neutral", "block_long": false, "block_short": false, "btc_chg": -0.19, "final_direction": null, "final_score": 0, "price": 0.3112, "price_chg_1h": -0.7, "sq_score": 0, "ml_score": 0, "vol_24h": 59733411.82458}, "LITEUSDT": {"sym": "LITEUSDT", "sl": 0, "ss": 0, "oh_score": 0, "od_score": 3, "rsi1h": 39.4, "rsi5m": 43.9, "fund": 0.0, "cvd": 13.6, "oi": 0.0, "long_pct": 79, "trend": "bearish", "ms4h": "bullish", "ms1h": "neutral", "block_long": false, "block_short": false, "btc_chg": -0.19, "final_direction": null, "final_score": 3, "price": 821.06, "price_chg_1h": -2.65, "sq_score": 0, "ml_score": 0, "vol_24h": 59529852.0218}, "ALLOUSDT": {"sym": "ALLOUSDT", "sl": 0, "ss": 0, "oh_score": 0, "od_score": 0, "rsi1h": 35.4, "rsi5m": 42.5, "fund": 0.005, "cvd": 1.8, "oi": 0.0, "long_pct": 47, "trend": "neutral", "ms4h": "bearish", "ms1h": "bearish", "block_long": true, "block_short": false, "btc_chg": -0.19, "final_direction": null, "final_score": 0, "price": 0.40456, "price_chg_1h": 2.81, "sq_score": 0, "ml_score": 0, "vol_24h": 59108628.93756}, "DOTUSDT": {"sym": "DOTUSDT", "sl": 0, "ss": 0, "oh_score": 0, "od_score": 0, "rsi1h": 31.8, "rsi5m": 48.1, "fund": -0.0128, "cvd": 0.0, "oi": 0.0, "long_pct": 61, "trend": "bearish", "ms4h": "bearish", "ms1h": "bearish", "block_long": true, "block_short": false, "btc_chg": -0.19, "final_direction": null, "final_score": 0, "price": 0.901, "price_chg_1h": -0.33, "sq_score": 0, "ml_score": 0, "vol_24h": 59202446.928}, "XMRUSDT": {"sym": "XMRUSDT", "sl": 0, "ss": 0, "oh_score": 0, "od_score": 0, "rsi1h": 48.2, "rsi5m": 63.8, "fund": 0.01, "cvd": -26.6, "oi": 0.0, "long_pct": 52, "trend": "bearish", "ms4h": "neutral", "ms1h": "bearish", "block_long": false, "block_short": false, "btc_chg": -0.19, "final_direction": null, "final_score": 0, "price": 316.38, "price_chg_1h": -0.42, "sq_score": 0, "ml_score": 0, "vol_24h": 56300030.75}, "ARMUSDT": {"sym": "ARMUSDT", "sl": 0, "ss": 0, "oh_score": 0, "od_score": 0, "rsi1h": 26.5, "rsi5m": 40.1, "fund": 0.0, "cvd": 19.4, "oi": 0.0, "long_pct": 61, "trend": "bearish", "ms4h": "neutral", "ms1h": "bearish", "block_long": false, "block_short": false, "btc_chg": -0.19, "final_direction": null, "final_score": 0, "price": 368.2, "price_chg_1h": -3.71, "sq_score": 0, "ml_score": 0, "vol_24h": 53499748.316}, "HOODUSDT": {"sym": "HOODUSDT", "sl": 0, "ss": 0, "oh_score": 0, "od_score": 0, "rsi1h": 39.5, "rsi5m": 48.8, "fund": 0.0, "cvd": -27.6, "oi": 0.0, "long_pct": 56, "trend": "neutral", "ms4h": "bearish", "ms1h": "bullish", "block_long": false, "block_short": false, "btc_chg": -0.19, "final_direction": null, "final_score": 0, "price": 103.16, "price_chg_1h": 0.72, "sq_score": 0, "ml_score": 0, "vol_24h": 52536017.2512}, "ASTERUSDT": {"sym": "ASTERUSDT", "sl": 0, "ss": 0, "oh_score": 0, "od_score": 0, "rsi1h": 36.7, "rsi5m": 57.8, "fund": -0.0049, "cvd": 0.0, "oi": 0.0, "long_pct": 53, "trend": "bearish", "ms4h": "bearish", "ms1h": "bearish", "block_long": true, "block_short": false, "btc_chg": -0.19, "final_direction": null, "final_score": 0, "price": 0.6216, "price_chg_1h": 0.1, "sq_score": 0, "ml_score": 0, "vol_24h": 47508367.2331}, "TRXUSDT": {"sym": "TRXUSDT", "sl": 0, "ss": 0, "oh_score": 0, "od_score": 3, "rsi1h": 39.6, "rsi5m": 52.5, "fund": -0.0155, "cvd": 0.0, "oi": 0.0, "long_pct": 63, "trend": "neutral", "ms4h": "bullish", "ms1h": "bearish", "block_long": false, "block_short": false, "btc_chg": -0.19, "final_direction": null, "final_score": 3, "price": 0.32895, "price_chg_1h": -0.24, "sq_score": 0, "ml_score": 0, "vol_24h": 46338188.87492}, "WDCUSDT": {"sym": "WDCUSDT", "sl": 0, "ss": 0, "oh_score": 0, "od_score": 0, "rsi1h": 31.7, "rsi5m": 45.7, "fund": 0.0, "cvd": 19.0, "oi": 0.0, "long_pct": 71, "trend": "neutral", "ms4h": "neutral", "ms1h": "neutral", "block_long": false, "block_short": false, "btc_chg": -0.19, "final_direction": null, "final_score": 0, "price": 672.36, "price_chg_1h": -1.88, "sq_score": 0, "ml_score": 0, "vol_24h": 45510595.1764}, "XPLUSDT": {"sym": "XPLUSDT", "sl": 0, "ss": 0, "oh_score": 3, "od_score": 0, "rsi1h": 47.4, "rsi5m": 60.1, "fund": 0.0014, "cvd": -15.4, "oi": 0.0, "long_pct": 40, "trend": "bearish", "ms4h": "bearish", "ms1h": "neutral", "block_long": false, "block_short": false, "btc_chg": -0.19, "final_direction": null, "final_score": 3, "price": 0.08918, "price_chg_1h": 3.4, "sq_score": 0, "ml_score": 0, "vol_24h": 44435991.63687}, "AAOIUSDT": {"sym": "AAOIUSDT", "sl": 0, "ss": 0, "oh_score": 0, "od_score": 5, "rsi1h": 42.8, "rsi5m": 55.0, "fund": 0.0, "cvd": 18.2, "oi": 0.0, "long_pct": 81, "trend": "bearish", "ms4h": "bullish", "ms1h": "neutral", "block_long": false, "block_short": false, "btc_chg": -0.19, "final_direction": null, "final_score": 5, "price": 147.73, "price_chg_1h": -8.92, "sq_score": 0, "ml_score": 0, "vol_24h": 39997197.8732}, "INJUSDT": {"sym": "INJUSDT", "sl": 0, "ss": 0, "oh_score": 0, "od_score": 0, "rsi1h": 30.9, "rsi5m": 42.6, "fund": -0.0133, "cvd": 3.8, "oi": 0.0, "long_pct": 35, "trend": "bearish", "ms4h": "bearish", "ms1h": "neutral", "block_long": false, "block_short": false, "btc_chg": -0.19, "final_direction": null, "final_score": 0, "price": 4.553, "price_chg_1h": -1.11, "sq_score": 0, "ml_score": 0, "vol_24h": 39483576.2299}, "GOOGLUSDT": {"sym": "GOOGLUSDT", "sl": 0, "ss": 0, "oh_score": 0, "od_score": 0, "rsi1h": 33.0, "rsi5m": 50.7, "fund": 0.0, "cvd": 0.0, "oi": 0.0, "long_pct": 82, "trend": "bearish", "ms4h": "bearish", "ms1h": "bearish", "block_long": true, "block_short": false, "btc_chg": -0.19, "final_direction": null, "final_score": 0, "price": 347.33, "price_chg_1h": 1.12, "sq_score": 0, "ml_score": 0, "vol_24h": 38558529.9273}, "TNSRUSDT": {"sym": "TNSRUSDT", "sl": 0, "ss": 0, "oh_score": 0, "od_score": 0, "rsi1h": 32.4, "rsi5m": 47.7, "fund": -0.0133, "cvd": -9.2, "oi": 0.0, "long_pct": 54, "trend": "neutral", "ms4h": "bearish", "ms1h": "neutral", "block_long": false, "block_short": false, "btc_chg": -0.19, "final_direction": null, "final_score": 0, "price": 0.03461, "price_chg_1h": -1.59, "sq_score": 0, "ml_score": 0, "vol_24h": 37745723.476098}, "JTOUSDT": {"sym": "JTOUSDT", "sl": 0, "ss": 0, "oh_score": 0, "od_score": 0, "rsi1h": 37.8, "rsi5m": 44.0, "fund": 0.0025, "cvd": -18.0, "oi": 0.0, "long_pct": 47, "trend": "bearish", "ms4h": "bearish", "ms1h": "neutral", "block_long": false, "block_short": false, "btc_chg": -0.19, "final_direction": null, "final_score": 0, "price": 0.6401, "price_chg_1h": 3.59, "sq_score": 0, "ml_score": 0, "vol_24h": 37425129.4704}, "PUMPUSDT": {"sym": "PUMPUSDT", "sl": 0, "ss": 0, "oh_score": 0, "od_score": 0, "rsi1h": 32.3, "rsi5m": 53.2, "fund": 0.003, "cvd": 0.0, "oi": 0.0, "long_pct": 39, "trend": "bearish", "ms4h": "bearish", "ms1h": "neutral", "block_long": false, "block_short": false, "btc_chg": -0.19, "final_direction": null, "final_score": 0, "price": 0.001388, "price_chg_1h": -0.29, "sq_score": 0, "ml_score": 0, "vol_24h": 37214232.222244}, "FETUSDT": {"sym": "FETUSDT", "sl": 0, "ss": 0, "oh_score": 0, "od_score": 0, "rsi1h": 36.4, "rsi5m": 57.9, "fund": 0.0031, "cvd": 0.0, "oi": 0.0, "long_pct": 45, "trend": "bearish", "ms4h": "bearish", "ms1h": "neutral", "block_long": false, "block_short": false, "btc_chg": -0.19, "final_direction": null, "final_score": 0, "price": 0.1732, "price_chg_1h": -0.17, "sq_score": 0, "ml_score": 0, "vol_24h": 35043323.1472}, "EIGENUSDT": {"sym": "EIGENUSDT", "sl": 0, "ss": 0, "oh_score": 0, "od_score": 0, "rsi1h": 32.9, "rsi5m": 40.2, "fund": 0.005, "cvd": -8.0, "oi": 0.0, "long_pct": 57, "trend": "neutral", "ms4h": "bearish", "ms1h": "bearish", "block_long": true, "block_short": false, "btc_chg": -0.19, "final_direction": null, "final_score": 0, "price": 0.2525, "price_chg_1h": -1.79, "sq_score": 0, "ml_score": 0, "vol_24h": 33636103.16394}, "1000SHIBUSDT": {"sym": "1000SHIBUSDT", "sl": 0, "ss": 0, "oh_score": 0, "od_score": 3, "rsi1h": 43.0, "rsi5m": 65.0, "fund": 0.0066, "cvd": 0.0, "oi": 0.0, "long_pct": 52, "trend": "bearish", "ms4h": "neutral", "ms1h": "neutral", "block_long": false, "block_short": false, "btc_chg": -0.19, "final_direction": null, "final_score": 3, "price": 0.004534, "price_chg_1h": 0.24, "sq_score": 0, "ml_score": 0, "vol_24h": 33341001.359799}, "VVVUSDT": {"sym": "VVVUSDT", "sl": 0, "ss": 0, "oh_score": 0, "od_score": 0, "rsi1h": 20.6, "rsi5m": 40.9, "fund": -0.0469, "cvd": 68.6, "oi": 0.0, "long_pct": 35, "trend": "bearish", "ms4h": "neutral", "ms1h": "neutral", "block_long": false, "block_short": false, "btc_chg": -0.19, "final_direction": null, "final_score": 0, "price": 13.912, "price_chg_1h": 2.98, "sq_score": 0, "ml_score": 0, "vol_24h": 31910002.65636}, "ARBUSDT": {"sym": "ARBUSDT", "sl": 0, "ss": 0, "oh_score": 0, "od_score": 2, "rsi1h": 31.9, "rsi5m": 58.2, "fund": -0.0163, "cvd": 0.0, "oi": 0.0, "long_pct": 53, "trend": "bearish", "ms4h": "neutral", "ms1h": "bearish", "block_long": false, "block_short": false, "btc_chg": -0.19, "final_direction": null, "final_score": 2, "price": 0.07833, "price_chg_1h": -0.81, "sq_score": 0, "ml_score": 0, "vol_24h": 31104236.442061}, "AXSUSDT": {"sym": "AXSUSDT", "sl": 0, "ss": 0, "oh_score": 0, "od_score": 0, "rsi1h": 44.9, "rsi5m": 52.7, "fund": 0.0004, "cvd": -7.4, "oi": 0.0, "long_pct": 56, "trend": "neutral", "ms4h": "bearish", "ms1h": "neutral", "block_long": false, "block_short": false, "btc_chg": -0.19, "final_direction": null, "final_score": 0, "price": 1.017, "price_chg_1h": -1.07, "sq_score": 0, "ml_score": 0, "vol_24h": 31018131.494}, "GUAUSDT": {"sym": "GUAUSDT", "sl": 0, "ss": 0, "oh_score": 0, "od_score": 0, "rsi1h": 30.6, "rsi5m": 52.3, "fund": -0.0685, "cvd": -18.8, "oi": 0.0, "long_pct": 50, "trend": "bearish", "ms4h": "bearish", "ms1h": "bearish", "block_long": true, "block_short": false, "btc_chg": -0.19, "final_direction": null, "final_score": 0, "price": 0.5108, "price_chg_1h": 26.37, "sq_score": 0, "ml_score": 0, "vol_24h": 30783458.9439}, "ALGOUSDT": {"sym": "ALGOUSDT", "sl": 0, "ss": 0, "oh_score": 0, "od_score": 0, "rsi1h": 65.8, "rsi5m": 84.3, "fund": 0.01, "cvd": 76.8, "oi": 0.0, "long_pct": 42, "trend": "neutral", "ms4h": "bearish", "ms1h": "neutral", "block_long": false, "block_short": false, "btc_chg": -0.19, "final_direction": null, "final_score": 0, "price": 0.0937, "price_chg_1h": 1.85, "sq_score": 0, "ml_score": 0, "vol_24h": 30265776.6236}, "FIDAUSDT": {"sym": "FIDAUSDT", "sl": 0, "ss": 0, "oh_score": 0, "od_score": 0, "rsi1h": 51.5, "rsi5m": 43.1, "fund": -0.1879, "cvd": 33.2, "oi": 0.0, "long_pct": 47, "trend": "neutral", "ms4h": "neutral", "ms1h": "neutral", "block_long": false, "block_short": false, "btc_chg": -0.19, "final_direction": null, "final_score": 0, "price": 0.0227, "price_chg_1h": -3.9, "sq_score": 0, "ml_score": 0, "vol_24h": 29536737.61521}, "AEROUSDT": {"sym": "AEROUSDT", "sl": 0, "ss": 0, "oh_score": 0, "od_score": 2, "rsi1h": 42.6, "rsi5m": 46.3, "fund": 0.005, "cvd": -0.2, "oi": 0.0, "long_pct": 65, "trend": "neutral", "ms4h": "bullish", "ms1h": "bearish", "block_long": false, "block_short": false, "btc_chg": -0.19, "final_direction": null, "final_score": 2, "price": 0.5019, "price_chg_1h": -4.51, "sq_score": 0, "ml_score": 0, "vol_24h": 27277062.13487}, "PENGUUSDT": {"sym": "PENGUUSDT", "sl": 0, "ss": 0, "oh_score": 0, "od_score": 0, "rsi1h": 31.6, "rsi5m": 47.9, "fund": -0.0019, "cvd": 83.4, "oi": 0.0, "long_pct": 33, "trend": "bearish", "ms4h": "bearish", "ms1h": "bearish", "block_long": true, "block_short": false, "btc_chg": -0.19, "final_direction": null, "final_score": 0, "price": 0.006199, "price_chg_1h": -2.32, "sq_score": 0, "ml_score": 0, "vol_24h": 28734803.363784}, "FARTCOINUSDT": {"sym": "FARTCOINUSDT", "sl": 0, "ss": 0, "oh_score": 0, "od_score": 0, "rsi1h": 38.4, "rsi5m": 58.6, "fund": 0.005, "cvd": -23.4, "oi": 0.0, "long_pct": 66, "trend": "bearish", "ms4h": "neutral", "ms1h": "neutral", "block_long": false, "block_short": false, "btc_chg": -0.19, "final_direction": null, "final_score": 0, "price": 0.1252, "price_chg_1h": 2.37, "sq_score": 0, "ml_score": 0, "vol_24h": 27504709.05866}, "RKLBUSDT": {"sym": "RKLBUSDT", "sl": 0, "ss": 0, "oh_score": 0, "od_score": 0, "rsi1h": 38.5, "rsi5m": 48.6, "fund": 0.0, "cvd": 6.4, "oi": 0.0, "long_pct": 79, "trend": "bearish", "ms4h": "bearish", "ms1h": "bullish", "block_long": false, "block_short": false, "btc_chg": -0.19, "final_direction": null, "final_score": 0, "price": 96.3, "price_chg_1h": -0.55, "sq_score": 0, "ml_score": 0, "vol_24h": 26579445.8577}, "ICPUSDT": {"sym": "ICPUSDT", "sl": 0, "ss": 0, "oh_score": 0, "od_score": 0, "rsi1h": 33.8, "rsi5m": 48.0, "fund": -0.0075, "cvd": 0.0, "oi": 0.0, "long_pct": 47, "trend": "bearish", "ms4h": "bearish", "ms1h": "neutral", "block_long": false, "block_short": false, "btc_chg": -0.19, "final_direction": null, "final_score": 0, "price": 2.159, "price_chg_1h": -0.18, "sq_score": 0, "ml_score": 0, "vol_24h": 23801081.184}, "OPGUSDT": {"sym": "OPGUSDT", "sl": 0.1828, "ss": 0, "oh_score": 0, "od_score": 0, "rsi1h": 76.4, "rsi5m": 75.1, "fund": 0.005, "cvd": -9.8, "oi": 0.0, "long_pct": 41, "trend": "neutral", "ms4h": "neutral", "ms1h": "neutral", "block_long": false, "block_short": false, "btc_chg": -0.19, "final_direction": "SHORT", "final_score": 6, "price": 0.1731, "price_chg_1h": 0.46, "sq_score": 0, "ml_score": 0, "vol_24h": 23830015.7534, "tp1": 0.1592, "rr": 1.44}, "HOMEUSDT": {"sym": "HOMEUSDT", "sl": 0, "ss": 0, "oh_score": 4, "od_score": 0, "rsi1h": 56.6, "rsi5m": 75.2, "fund": -0.0073, "cvd": -51.0, "oi": 0.0, "long_pct": 32, "trend": "neutral", "ms4h": "bearish", "ms1h": "bullish", "block_long": false, "block_short": false, "btc_chg": -0.19, "final_direction": null, "final_score": 4, "price": 0.02083, "price_chg_1h": 1.76, "sq_score": 0, "ml_score": 0, "vol_24h": 22379873.390898}, "WIFUSDT": {"sym": "WIFUSDT", "sl": 0, "ss": 0, "oh_score": 0, "od_score": 0, "rsi1h": 36.6, "rsi5m": 57.3, "fund": -0.002, "cvd": 0.0, "oi": 0.0, "long_pct": 53, "trend": "bearish", "ms4h": "bearish", "ms1h": "neutral", "block_long": false, "block_short": false, "btc_chg": -0.19, "final_direction": null, "final_score": 0, "price": 0.1561, "price_chg_1h": -0.76, "sq_score": 0, "ml_score": 0, "vol_24h": 22168468.03564}, "IPUSDT": {"sym": "IPUSDT", "sl": 0, "ss": 0, "oh_score": 0, "od_score": 0, "rsi1h": 35.0, "rsi5m": 46.4, "fund": 0.005, "cvd": -3.8, "oi": 0.0, "long_pct": 70, "trend": "neutral", "ms4h": "neutral", "ms1h": "neutral", "block_long": false, "block_short": false, "btc_chg": -0.19, "final_direction": null, "final_score": 0, "price": 0.312, "price_chg_1h": 2.7, "sq_score": 0, "ml_score": 0, "vol_24h": 22180447.61968}, "CHZUSDT": {"sym": "CHZUSDT", "sl": 0, "ss": 0, "oh_score": 0, "od_score": 0, "rsi1h": 30.8, "rsi5m": 49.9, "fund": -0.0014, "cvd": 0.0, "oi": 0.0, "long_pct": 42, "trend": "bearish", "ms4h": "bearish", "ms1h": "neutral", "block_long": false, "block_short": false, "btc_chg": -0.19, "final_direction": null, "final_score": 0, "price": 0.01919, "price_chg_1h": 0.26, "sq_score": 0, "ml_score": 0, "vol_24h": 22091391.38033}, "ETCUSDT": {"sym": "ETCUSDT", "sl": 0, "ss": 0, "oh_score": 0, "od_score": 0, "rsi1h": 27.7, "rsi5m": 33.9, "fund": -0.001, "cvd": 3.2, "oi": 0.0, "long_pct": 52, "trend": "bearish", "ms4h": "neutral", "ms1h": "bearish", "block_long": false, "block_short": false, "btc_chg": -0.19, "final_direction": null, "final_score": 0, "price": 6.937, "price_chg_1h": -0.89, "sq_score": 0, "ml_score": 0, "vol_24h": 21238062.605}, "STGUSDT": {"sym": "STGUSDT", "sl": 0, "ss": 0, "oh_score": 0, "od_score": 0, "rsi1h": 39.2, "rsi5m": 52.4, "fund": -0.0027, "cvd": -70.8, "oi": 0.0, "long_pct": 33, "trend": "bearish", "ms4h": "bearish", "ms1h": "neutral", "block_long": false, "block_short": false, "btc_chg": -0.19, "final_direction": null, "final_score": 0, "price": 0.1825, "price_chg_1h": -3.08, "sq_score": 0, "ml_score": 0, "vol_24h": 21265662.6386}, "DASHUSDT": {"sym": "DASHUSDT", "sl": 0, "ss": 0, "oh_score": 1, "od_score": 0, "rsi1h": 51.2, "rsi5m": 59.3, "fund": 0.0073, "cvd": -5.2, "oi": 0.0, "long_pct": 40, "trend": "bearish", "ms4h": "neutral", "ms1h": "bearish", "block_long": false, "block_short": false, "btc_chg": -0.19, "final_direction": null, "final_score": 1, "price": 35.75, "price_chg_1h": 1.76, "sq_score": 0, "ml_score": 0, "vol_24h": 20921295.62}, "OPUSDT": {"sym": "OPUSDT", "sl": 0, "ss": 0, "oh_score": 0, "od_score": 2, "rsi1h": 37.5, "rsi5m": 58.3, "fund": 0.0064, "cvd": 34.6, "oi": 0.0, "long_pct": 50, "trend": "bearish", "ms4h": "neutral", "ms1h": "bearish", "block_long": false, "block_short": false, "btc_chg": -0.19, "final_direction": null, "final_score": 2, "price": 0.0982, "price_chg_1h": 0.2, "sq_score": 0, "ml_score": 0, "vol_24h": 21153939.2972}, "JUPUSDT": {"sym": "JUPUSDT", "sl": 0, "ss": 0, "oh_score": 0, "od_score": 1, "rsi1h": 37.5, "rsi5m": 46.1, "fund": -0.0102, "cvd": -2.2, "oi": 0.0, "long_pct": 63, "trend": "neutral", "ms4h": "neutral", "ms1h": "neutral", "block_long": false, "block_short": false, "btc_chg": -0.19, "final_direction": null, "final_score": 1, "price": 0.2017, "price_chg_1h": -1.27, "sq_score": 0, "ml_score": 0, "vol_24h": 20705041.1393}, "APTUSDT": {"sym": "APTUSDT", "sl": 0, "ss": 0, "oh_score": 0, "od_score": 0, "rsi1h": 33.0, "rsi5m": 44.5, "fund": 0.0005, "cvd": 0.0, "oi": 0.0, "long_pct": 55, "trend": "bearish", "ms4h": "neutral", "ms1h": "bearish", "block_long": false, "block_short": false, "btc_chg": -0.19, "final_direction": null, "final_score": 0, "price": 0.6361, "price_chg_1h": 0.7, "sq_score": 0, "ml_score": 0, "vol_24h": 20001656.55308}, "NATGASUSDT": {"sym": "NATGASUSDT", "sl": 0, "ss": 0, "oh_score": 0, "od_score": 1, "rsi1h": 35.3, "rsi5m": 42.1, "fund": 0.0, "cvd": 0.0, "oi": 0.0, "long_pct": 54, "trend": "neutral", "ms4h": "neutral", "ms1h": "bullish", "block_long": false, "block_short": false, "btc_chg": -0.19, "final_direction": null, "final_score": 1, "price": 3.192, "price_chg_1h": -1.12, "sq_score": 0, "ml_score": 0, "vol_24h": 19677478.8737}, "WLFIUSDT": {"sym": "WLFIUSDT", "sl": 0, "ss": 0, "oh_score": 0, "od_score": 0, "rsi1h": 39.3, "rsi5m": 48.3, "fund": 0.005, "cvd": -14.2, "oi": 0.0, "long_pct": 43, "trend": "bearish", "ms4h": "bearish", "ms1h": "bearish", "block_long": true, "block_short": false, "btc_chg": -0.19, "final_direction": null, "final_score": 0, "price": 0.05897, "price_chg_1h": 2.09, "sq_score": 0, "ml_score": 0, "vol_24h": 18598848.71661}, "BSBUSDT": {"sym": "BSBUSDT", "sl": 0, "ss": 0, "oh_score": 0, "od_score": 0, "rsi1h": 54.2, "rsi5m": 57.8, "fund": 0.008, "cvd": -6.0, "oi": 0.0, "long_pct": 63, "trend": "bearish", "ms4h": "neutral", "ms1h": "neutral", "block_long": false, "block_short": false, "btc_chg": -0.19, "final_direction": null, "final_score": 0, "price": 0.32195, "price_chg_1h": -4.59, "sq_score": 0, "ml_score": 0, "vol_24h": 18533797.88005}, "COINUSDT": {"sym": "COINUSDT", "sl": 0, "ss": 0, "oh_score": 0, "od_score": 0, "rsi1h": 38.6, "rsi5m": 46.0, "fund": 0.0, "cvd": -36.6, "oi": 0.0, "long_pct": 65, "trend": "bearish", "ms4h": "neutral", "ms1h": "neutral", "block_long": false, "block_short": false, "btc_chg": -0.19, "final_direction": null, "final_score": 0, "price": 158.3, "price_chg_1h": -1.0, "sq_score": 0, "ml_score": 0, "vol_24h": 18611486.3727}, "TSMUSDT": {"sym": "TSMUSDT", "sl": 0, "ss": 0, "oh_score": 0, "od_score": 0, "rsi1h": 27.2, "rsi5m": 44.2, "fund": 0.0296, "cvd": -37.0, "oi": 0.0, "long_pct": 76, "trend": "neutral", "ms4h": "bearish", "ms1h": "neutral", "block_long": false, "block_short": false, "btc_chg": -0.19, "final_direction": null, "final_score": 0, "price": 439.4, "price_chg_1h": -1.75, "sq_score": 0, "ml_score": 0, "vol_24h": 18549939.9435}, "AXTIUSDT": {"sym": "AXTIUSDT", "sl": 0, "ss": 0, "oh_score": 0, "od_score": 0, "rsi1h": 34.1, "rsi5m": 35.7, "fund": 0.0, "cvd": -0.2, "oi": 0.0, "long_pct": 78, "trend": "bearish", "ms4h": "neutral", "ms1h": "neutral", "block_long": false, "block_short": false, "btc_chg": -0.19, "final_direction": null, "final_score": 0, "price": 77.32, "price_chg_1h": -9.04, "sq_score": 0, "ml_score": 0, "vol_24h": 18315464.9081}, "HBARUSDT": {"sym": "HBARUSDT", "sl": 0, "ss": 0, "oh_score": 0, "od_score": 0, "rsi1h": 37.1, "rsi5m": 58.1, "fund": 0.0057, "cvd": 0.0, "oi": 0.0, "long_pct": 42, "trend": "bearish", "ms4h": "bearish", "ms1h": "bearish", "block_long": true, "block_short": false, "btc_chg": -0.19, "final_direction": null, "final_score": 0, "price": 0.07727, "price_chg_1h": -0.46, "sq_score": 0, "ml_score": 0, "vol_24h": 18362536.35926}, "RENDERUSDT": {"sym": "RENDERUSDT", "sl": 0, "ss": 0, "oh_score": 0, "od_score": 3, "rsi1h": 33.4, "rsi5m": 54.5, "fund": -0.0119, "cvd": 0.0, "oi": 0.0, "long_pct": 36, "trend": "bearish", "ms4h": "neutral", "ms1h": "bearish", "block_long": false, "block_short": false, "btc_chg": -0.19, "final_direction": null, "final_score": 3, "price": 1.56, "price_chg_1h": -0.83, "sq_score": 0, "ml_score": 0, "vol_24h": 18257340.02}, "1000BONKUSDT": {"sym": "1000BONKUSDT", "sl": 0, "ss": 0, "oh_score": 0, "od_score": 0, "rsi1h": 34.5, "rsi5m": 54.1, "fund": 0.0005, "cvd": 0.0, "oi": 0.0, "long_pct": 56, "trend": "bearish", "ms4h": "bearish", "ms1h": "bearish", "block_long": true, "block_short": false, "btc_chg": -0.19, "final_direction": null, "final_score": 0, "price": 0.004354, "price_chg_1h": -1.27, "sq_score": 0, "ml_score": 0, "vol_24h": 18028104.05492}, "RIVERUSDT": {"sym": "RIVERUSDT", "sl": 0, "ss": 0, "oh_score": 0, "od_score": 0, "rsi1h": 26.6, "rsi5m": 39.3, "fund": 0.005, "cvd": 42.8, "oi": 0.0, "long_pct": 72, "trend": "bearish", "ms4h": "bearish", "ms1h": "bearish", "block_long": true, "block_short": false, "btc_chg": -0.19, "final_direction": null, "final_score": 0, "price": 4.301, "price_chg_1h": -3.09, "sq_score": 0, "ml_score": 0, "vol_24h": 17585067.1993}, "QCOMUSDT": {"sym": "QCOMUSDT", "sl": 0, "ss": 0, "oh_score": 0, "od_score": 0, "rsi1h": 22.0, "rsi5m": 42.2, "fund": 0.0, "cvd": -43.6, "oi": 0.0, "long_pct": 67, "trend": "bearish", "ms4h": "bearish", "ms1h": "bearish", "block_long": true, "block_short": false, "btc_chg": -0.19, "final_direction": null, "final_score": 0, "price": 204.69, "price_chg_1h": -1.95, "sq_score": 0, "ml_score": 0, "vol_24h": 17487894.765}, "MSFTUSDT": {"sym": "MSFTUSDT", "sl": 0, "ss": 0, "oh_score": 5, "od_score": 0, "rsi1h": 53.5, "rsi5m": 57.4, "fund": 0.0089, "cvd": 0.0, "oi": 0.0, "long_pct": 87, "trend": "bearish", "ms4h": "bearish", "ms1h": "neutral", "block_long": false, "block_short": false, "btc_chg": -0.19, "final_direction": null, "final_score": 5, "price": 374.39, "price_chg_1h": 0.57, "sq_score": 0, "ml_score": 0, "vol_24h": 17262709.6577}, "OPNUSDT": {"sym": "OPNUSDT", "sl": 0, "ss": 0, "oh_score": 2, "od_score": 0, "rsi1h": 61.3, "rsi5m": 76.6, "fund": 0.005, "cvd": 61.0, "oi": 0.0, "long_pct": 43, "trend": "neutral", "ms4h": "neutral", "ms1h": "neutral", "block_long": false, "block_short": false, "btc_chg": -0.19, "final_direction": null, "final_score": 2, "price": 0.07493, "price_chg_1h": 0.89, "sq_score": 0, "ml_score": 0, "vol_24h": 16949413.70175}, "WUSDT": {"sym": "WUSDT", "sl": 0, "ss": 0, "oh_score": 0, "od_score": 2, "rsi1h": 38.1, "rsi5m": 52.2, "fund": 0.005, "cvd": 18.6, "oi": 0.0, "long_pct": 59, "trend": "neutral", "ms4h": "neutral", "ms1h": "bullish", "block_long": false, "block_short": false, "btc_chg": -0.19, "final_direction": null, "final_score": 2, "price": 0.01035, "price_chg_1h": -2.54, "sq_score": 0, "ml_score": 0, "vol_24h": 16828180.815111}, "VIRTUALUSDT": {"sym": "VIRTUALUSDT", "sl": 0, "ss": 0, "oh_score": 0, "od_score": 3, "rsi1h": 32.3, "rsi5m": 51.2, "fund": -0.0108, "cvd": 0.0, "oi": 0.0, "long_pct": 35, "trend": "bearish", "ms4h": "neutral", "ms1h": "bearish", "block_long": false, "block_short": false, "btc_chg": -0.19, "final_direction": null, "final_score": 3, "price": 0.5692, "price_chg_1h": 0.51, "sq_score": 0, "ml_score": 0, "vol_24h": 16459085.57204}, "AVGOUSDT": {"sym": "AVGOUSDT", "sl": 0, "ss": 0, "oh_score": 0, "od_score": 5, "rsi1h": 21.7, "rsi5m": 44.2, "fund": 0.0, "cvd": 29.8, "oi": 0.0, "long_pct": 82, "trend": "bearish", "ms4h": "neutral", "ms1h": "bearish", "block_long": false, "block_short": false, "btc_chg": -0.19, "final_direction": null, "final_score": 5, "price": 382.08, "price_chg_1h": 1.22, "sq_score": 0, "ml_score": 0, "vol_24h": 15639557.0432}, "LDOUSDT": {"sym": "LDOUSDT", "sl": 0, "ss": 0, "oh_score": 0, "od_score": 0, "rsi1h": 26.7, "rsi5m": 47.1, "fund": -0.0016, "cvd": 0.0, "oi": 0.0, "long_pct": 53, "trend": "bearish", "ms4h": "bearish", "ms1h": "neutral", "block_long": false, "block_short": false, "btc_chg": -0.19, "final_direction": null, "final_score": 0, "price": 0.2567, "price_chg_1h": 0.27, "sq_score": 0, "ml_score": 0, "vol_24h": 15604448.7616}, "SAHARAUSDT": {"sym": "SAHARAUSDT", "sl": 0, "ss": 0, "oh_score": 0, "od_score": 0, "rsi1h": 28.1, "rsi5m": 45.8, "fund": -0.0144, "cvd": -44.2, "oi": 0.0, "long_pct": 33, "trend": "bearish", "ms4h": "bearish", "ms1h": "neutral", "block_long": false, "block_short": false, "btc_chg": -0.19, "final_direction": null, "final_score": 0, "price": 0.01153, "price_chg_1h": 0.44, "sq_score": 0, "ml_score": 0, "vol_24h": 15477390.97098}, "ZROUSDT": {"sym": "ZROUSDT", "sl": 0, "ss": 0, "oh_score": 0, "od_score": 0, "rsi1h": 48.2, "rsi5m": 38.5, "fund": 0.005, "cvd": 25.2, "oi": 0.0, "long_pct": 43, "trend": "bearish", "ms4h": "neutral", "ms1h": "bearish", "block_long": false, "block_short": false, "btc_chg": -0.19, "final_direction": null, "final_score": 0, "price": 0.931, "price_chg_1h": -3.78, "sq_score": 0, "ml_score": 0, "vol_24h": 15185349.20333}, "ENSOUSDT": {"sym": "ENSOUSDT", "sl": 0, "ss": 0, "oh_score": 0, "od_score": 0, "rsi1h": 47.7, "rsi5m": 32.0, "fund": -0.0051, "cvd": -75.2, "oi": 0.0, "long_pct": 61, "trend": "neutral", "ms4h": "neutral", "ms1h": "neutral", "block_long": false, "block_short": false, "btc_chg": -0.19, "final_direction": null, "final_score": 0, "price": 0.63, "price_chg_1h": -3.7, "sq_score": 0, "ml_score": 0, "vol_24h": 14912105.46377}, "MEGAUSDT": {"sym": "MEGAUSDT", "sl": 0, "ss": 0, "oh_score": 3, "od_score": 0, "rsi1h": 46.6, "rsi5m": 63.2, "fund": 0.0009, "cvd": -45.0, "oi": 0.0, "long_pct": 43, "trend": "bearish", "ms4h": "bearish", "ms1h": "bearish", "block_long": true, "block_short": false, "btc_chg": -0.19, "final_direction": null, "final_score": 3, "price": 0.0539, "price_chg_1h": -0.41, "sq_score": 0, "ml_score": 0, "vol_24h": 14743053.33225}, "GWEIUSDT": {"sym": "GWEIUSDT", "sl": 0, "ss": 0, "oh_score": 1, "od_score": 2, "rsi1h": 44.0, "rsi5m": 47.7, "fund": 0.005, "cvd": 37.0, "oi": 0.0, "long_pct": 47, "trend": "neutral", "ms4h": "neutral", "ms1h": "bearish", "block_long": false, "block_short": false, "btc_chg": -0.19, "final_direction": null, "final_score": 2, "price": 0.1203, "price_chg_1h": 1.18, "sq_score": 0, "ml_score": 0, "vol_24h": 14413723.49943}, "SKYAIUSDT": {"sym": "SKYAIUSDT", "sl": 0, "ss": 0, "oh_score": 0, "od_score": 0, "rsi1h": 54.0, "rsi5m": 56.6, "fund": 0.005, "cvd": 4.4, "oi": 0.0, "long_pct": 51, "trend": "bearish", "ms4h": "bearish", "ms1h": "bullish", "block_long": false, "block_short": false, "btc_chg": -0.19, "final_direction": null, "final_score": 0, "price": 0.33003, "price_chg_1h": -4.54, "sq_score": 0, "ml_score": 0, "vol_24h": 14158505.96447}, "CRWVUSDT": {"sym": "CRWVUSDT", "sl": 0, "ss": 0, "oh_score": 0, "od_score": 0, "rsi1h": 26.9, "rsi5m": 33.6, "fund": 0.0, "cvd": -50.4, "oi": 0.0, "long_pct": 67, "trend": "bearish", "ms4h": "neutral", "ms1h": "bullish", "block_long": false, "block_short": false, "btc_chg": -0.19, "final_direction": null, "final_score": 0, "price": 105.57, "price_chg_1h": 0.7, "sq_score": 0, "ml_score": 0, "vol_24h": 14059056.919}, "ORCLUSDT": {"sym": "ORCLUSDT", "sl": 0, "ss": 0, "oh_score": 0, "od_score": 1, "rsi1h": 33.9, "rsi5m": 59.2, "fund": 0.0, "cvd": -13.8, "oi": 0.0, "long_pct": 77, "trend": "neutral", "ms4h": "neutral", "ms1h": "bearish", "block_long": false, "block_short": false, "btc_chg": -0.19, "final_direction": null, "final_score": 1, "price": 166.29, "price_chg_1h": -2.97, "sq_score": 0, "ml_score": 0, "vol_24h": 13949541.85}, "MOVRUSDT": {"sym": "MOVRUSDT", "sl": 0, "ss": 0, "oh_score": 0, "od_score": 0, "rsi1h": 51.6, "rsi5m": 30.1, "fund": 0.005, "cvd": -6.6, "oi": 0.0, "long_pct": 56, "trend": "neutral", "ms4h": "neutral", "ms1h": "neutral", "block_long": false, "block_short": false, "btc_chg": -0.19, "final_direction": null, "final_score": 0, "price": 1.187, "price_chg_1h": -3.5, "sq_score": 0, "ml_score": 0, "vol_24h": 13809450.76421}, "AAPLUSDT": {"sym": "AAPLUSDT", "sl": 0, "ss": 0, "oh_score": 0, "od_score": 0, "rsi1h": 34.3, "rsi5m": 39.1, "fund": 0.0, "cvd": -30.6, "oi": 0.0, "long_pct": 64, "trend": "neutral", "ms4h": "neutral", "ms1h": "bearish", "block_long": false, "block_short": false, "btc_chg": -0.19, "final_direction": null, "final_score": 0, "price": 296.04, "price_chg_1h": 0.38, "sq_score": 0, "ml_score": 0, "vol_24h": 13738762.0825}, "CRVUSDT": {"sym": "CRVUSDT", "sl": 0, "ss": 0, "oh_score": 0, "od_score": 0, "rsi1h": 39.3, "rsi5m": 50.3, "fund": -0.0057, "cvd": 0.0, "oi": 0.0, "long_pct": 37, "trend": "bearish", "ms4h": "bearish", "ms1h": "neutral", "block_long": false, "block_short": false, "btc_chg": -0.19, "final_direction": null, "final_score": 0, "price": 0.2044, "price_chg_1h": -0.05, "sq_score": 0, "ml_score": 0, "vol_24h": 13533637.04838}, "PENDLEUSDT": {"sym": "PENDLEUSDT", "sl": 0, "ss": 0, "oh_score": 0, "od_score": 0, "rsi1h": 32.4, "rsi5m": 55.6, "fund": -0.0049, "cvd": 0.0, "oi": 0.0, "long_pct": 45, "trend": "bearish", "ms4h": "bearish", "ms1h": "neutral", "block_long": false, "block_short": false, "btc_chg": -0.19, "final_direction": null, "final_score": 0, "price": 1.3022, "price_chg_1h": -0.63, "sq_score": 0, "ml_score": 0, "vol_24h": 13417666.6947}, "XPTUSDT": {"sym": "XPTUSDT", "sl": 0, "ss": 0, "oh_score": 0, "od_score": 0, "rsi1h": 37.1, "rsi5m": 53.0, "fund": 0.0, "cvd": -56.4, "oi": 0.0, "long_pct": 67, "trend": "neutral", "ms4h": "neutral", "ms1h": "neutral", "block_long": false, "block_short": false, "btc_chg": -0.19, "final_direction": null, "final_score": 0, "price": 1660.85, "price_chg_1h": 1.06, "sq_score": 0, "ml_score": 0, "vol_24h": 13200319.0004}, "SLXUSDT": {"sym": "SLXUSDT", "sl": 0, "ss": 0, "oh_score": 0, "od_score": 0, "rsi1h": 49.8, "rsi5m": 58.9, "fund": 0.0275, "cvd": 12.6, "oi": 0.0, "long_pct": 55, "trend": "bullish", "ms4h": "bullish", "ms1h": "neutral", "block_long": false, "block_short": false, "btc_chg": -0.19, "final_direction": null, "final_score": 0, "price": 0.2022, "price_chg_1h": 1.64, "sq_score": 0, "ml_score": 0, "vol_24h": 13120060.05166}, "METUSDT": {"sym": "METUSDT", "sl": 0, "ss": 0, "oh_score": 0, "od_score": 0, "rsi1h": 48.3, "rsi5m": 46.1, "fund": 0.0021, "cvd": -11.8, "oi": 0.0, "long_pct": 55, "trend": "neutral", "ms4h": "neutral", "ms1h": "bullish", "block_long": false, "block_short": false, "btc_chg": -0.19, "final_direction": null, "final_score": 0, "price": 0.1561, "price_chg_1h": -3.88, "sq_score": 0, "ml_score": 0, "vol_24h": 13104192.2293}, "CCUSDT": {"sym": "CCUSDT", "sl": 0, "ss": 0, "oh_score": 1, "od_score": 0, "rsi1h": 55.4, "rsi5m": 66.6, "fund": 0.0028, "cvd": 0.0, "oi": 0.0, "long_pct": 48, "trend": "neutral", "ms4h": "neutral", "ms1h": "bearish", "block_long": false, "block_short": false, "btc_chg": -0.19, "final_direction": null, "final_score": 1, "price": 0.15209, "price_chg_1h": 0.6, "sq_score": 0, "ml_score": 0, "vol_24h": 13021831.26274}, "LUMIAUSDT": {"sym": "LUMIAUSDT", "sl": 0, "ss": 0, "oh_score": 0, "od_score": 0, "rsi1h": 37.4, "rsi5m": 31.0, "fund": 0.005, "cvd": -52.6, "oi": 0.0, "long_pct": 51, "trend": "neutral", "ms4h": "neutral", "ms1h": "bearish", "block_long": false, "block_short": false, "btc_chg": -0.19, "final_direction": null, "final_score": 0, "price": 0.12386, "price_chg_1h": 2.73, "sq_score": 0, "ml_score": 0, "vol_24h": 12885226.308972}, "PRLUSDT": {"sym": "PRLUSDT", "sl": 0, "ss": 0, "oh_score": 0, "od_score": 0, "rsi1h": 51.4, "rsi5m": 58.8, "fund": 0.005, "cvd": -9.4, "oi": 0.0, "long_pct": 51, "trend": "neutral", "ms4h": "neutral", "ms1h": "neutral", "block_long": false, "block_short": false, "btc_chg": -0.19, "final_direction": null, "final_score": 0, "price": 0.1408, "price_chg_1h": -2.36, "sq_score": 0, "ml_score": 0, "vol_24h": 12927063.6575}, "EDGEUSDT": {"sym": "EDGEUSDT", "sl": 0, "ss": 0, "oh_score": 0, "od_score": 0, "rsi1h": 31.9, "rsi5m": 46.4, "fund": 0.0124, "cvd": -41.0, "oi": 0.0, "long_pct": 63, "trend": "neutral", "ms4h": "neutral", "ms1h": "neutral", "block_long": false, "block_short": false, "btc_chg": -0.19, "final_direction": null, "final_score": 0, "price": 0.3826, "price_chg_1h": 4.91, "sq_score": 0, "ml_score": 0, "vol_24h": 12827286.2269}, "METAUSDT": {"sym": "METAUSDT", "sl": 0, "ss": 0, "oh_score": 0, "od_score": 0, "rsi1h": 31.1, "rsi5m": 41.1, "fund": 0.0, "cvd": 42.0, "oi": 0.0, "long_pct": 70, "trend": "bearish", "ms4h": "bearish", "ms1h": "bearish", "block_long": true, "block_short": false, "btc_chg": -0.19, "final_direction": null, "final_score": 0, "price": 564.28, "price_chg_1h": 0.76, "sq_score": 0, "ml_score": 0, "vol_24h": 12586893.2142}, "ATOMUSDT": {"sym": "ATOMUSDT", "sl": 0, "ss": 0, "oh_score": 0, "od_score": 4, "rsi1h": 43.3, "rsi5m": 67.0, "fund": 0.0002, "cvd": 51.6, "oi": 0.0, "long_pct": 54, "trend": "neutral", "ms4h": "neutral", "ms1h": "neutral", "block_long": false, "block_short": false, "btc_chg": -0.19, "final_direction": null, "final_score": 4, "price": 1.72, "price_chg_1h": -2.71, "sq_score": 0, "ml_score": 0, "vol_24h": 12574699.126}, "ORDIUSDT": {"sym": "ORDIUSDT", "sl": 0, "ss": 0, "oh_score": 0, "od_score": 0, "rsi1h": 36.4, "rsi5m": 46.8, "fund": -0.0002, "cvd": 0.0, "oi": 0.0, "long_pct": 46, "trend": "bearish", "ms4h": "bearish", "ms1h": "bearish", "block_long": true, "block_short": false, "btc_chg": -0.19, "final_direction": null, "final_score": 0, "price": 3.116, "price_chg_1h": -0.67, "sq_score": 0, "ml_score": 0, "vol_24h": 12392347.6571}, "PLAYUSDT": {"sym": "PLAYUSDT", "sl": 0, "ss": 0, "oh_score": 0, "od_score": 0, "rsi1h": 46.3, "rsi5m": 56.6, "fund": 0.058, "cvd": 8.6, "oi": 0.0, "long_pct": 59, "trend": "neutral", "ms4h": "neutral", "ms1h": "bearish", "block_long": false, "block_short": false, "btc_chg": -0.19, "final_direction": null, "final_score": 0, "price": 0.03549, "price_chg_1h": -2.77, "sq_score": 0, "ml_score": 0, "vol_24h": 12405779.46469}, "1000LUNCUSDT": {"sym": "1000LUNCUSDT", "sl": 0, "ss": 0, "oh_score": 0, "od_score": 4, "rsi1h": 32.6, "rsi5m": 53.6, "fund": 0.0019, "cvd": 13.6, "oi": 0.0, "long_pct": 39, "trend": "neutral", "ms4h": "neutral", "ms1h": "bullish", "block_long": false, "block_short": false, "btc_chg": -0.19, "final_direction": null, "final_score": 4, "price": 0.06329, "price_chg_1h": -1.48, "sq_score": 0, "ml_score": 0, "vol_24h": 11872498.4582}, "\u9f99\u867eUSDT": {"sym": "\u9f99\u867eUSDT", "sl": 0, "ss": 0, "oh_score": 0, "od_score": 0, "rsi1h": 60.6, "rsi5m": 59.2, "fund": 0.0215, "cvd": -35.0, "oi": 0.0, "long_pct": 63, "trend": "neutral", "ms4h": "neutral", "ms1h": "bearish", "block_long": false, "block_short": false, "btc_chg": -0.19, "final_direction": null, "final_score": 0, "price": 0.011171, "price_chg_1h": -6.98, "sq_score": 0, "ml_score": 0, "vol_24h": 11617599.666269}, "OPENAIUSDT": {"sym": "OPENAIUSDT", "sl": 0, "ss": 0, "oh_score": 2, "od_score": 0, "rsi1h": 40.1, "rsi5m": 63.7, "fund": 0.005, "cvd": 0.0, "oi": 0.0, "long_pct": 57, "trend": "neutral", "ms4h": "neutral", "ms1h": "neutral", "block_long": false, "block_short": false, "btc_chg": -0.19, "final_direction": null, "final_score": 2, "price": 1330.01, "price_chg_1h": -0.83, "sq_score": 0, "ml_score": 0, "vol_24h": 11447943.501}, "SANDUSDT": {"sym": "SANDUSDT", "sl": 0, "ss": 0, "oh_score": 0, "od_score": 0, "rsi1h": 25.5, "rsi5m": 49.8, "fund": -0.0018, "cvd": -3.4, "oi": 0.0, "long_pct": 62, "trend": "neutral", "ms4h": "bearish", "ms1h": "neutral", "block_long": false, "block_short": false, "btc_chg": -0.19, "final_direction": null, "final_score": 0, "price": 0.05236, "price_chg_1h": 0.27, "sq_score": 0, "ml_score": 0, "vol_24h": 11183006.48698}, "CHIPUSDT": {"sym": "CHIPUSDT", "sl": 0, "ss": 0, "oh_score": 0, "od_score": 0, "rsi1h": 35.9, "rsi5m": 45.5, "fund": -0.0623, "cvd": -33.6, "oi": 0.0, "long_pct": 48, "trend": "bearish", "ms4h": "bearish", "ms1h": "bearish", "block_long": true, "block_short": false, "btc_chg": -0.19, "final_direction": null, "final_score": 0, "price": 0.03332, "price_chg_1h": 1.93, "sq_score": 0, "ml_score": 0, "vol_24h": 10827509.3509}, "AMZNUSDT": {"sym": "AMZNUSDT", "sl": 0, "ss": 0, "oh_score": 0, "od_score": 0, "rsi1h": 36.2, "rsi5m": 49.7, "fund": 0.0, "cvd": -29.6, "oi": 0.0, "long_pct": 70, "trend": "neutral", "ms4h": "neutral", "ms1h": "neutral", "block_long": false, "block_short": false, "btc_chg": -0.19, "final_direction": null, "final_score": 0, "price": 234.84, "price_chg_1h": 1.49, "sq_score": 0, "ml_score": 0, "vol_24h": 10608446.1927}, "USARUSDT": {"sym": "USARUSDT", "sl": 0, "ss": 0, "oh_score": 0, "od_score": 0, "rsi1h": 24.0, "rsi5m": 50.8, "fund": 0.0, "cvd": -4.2, "oi": 0.0, "long_pct": 76, "trend": "neutral", "ms4h": "neutral", "ms1h": "bearish", "block_long": false, "block_short": false, "btc_chg": -0.19, "final_direction": null, "final_score": 0, "price": 22.94, "price_chg_1h": -0.04, "sq_score": 0, "ml_score": 0, "vol_24h": 10575866.5592}, "SPXUSDT": {"sym": "SPXUSDT", "sl": 0, "ss": 0, "oh_score": 0, "od_score": 2, "rsi1h": 24.7, "rsi5m": 42.0, "fund": 0.005, "cvd": 3.2, "oi": 0.0, "long_pct": 52, "trend": "neutral", "ms4h": "neutral", "ms1h": "bearish", "block_long": false, "block_short": false, "btc_chg": -0.19, "final_direction": null, "final_score": 2, "price": 0.3431, "price_chg_1h": 0.0, "sq_score": 0, "ml_score": 0, "vol_24h": 10516481.5617}, "PLTRUSDT": {"sym": "PLTRUSDT", "sl": 0, "ss": 0, "oh_score": 0, "od_score": 2, "rsi1h": 41.0, "rsi5m": 53.1, "fund": 0.0, "cvd": 26.4, "oi": 0.0, "long_pct": 72, "trend": "neutral", "ms4h": "neutral", "ms1h": "neutral", "block_long": false, "block_short": false, "btc_chg": -0.19, "final_direction": null, "final_score": 2, "price": 116.54, "price_chg_1h": -2.42, "sq_score": 0, "ml_score": 0, "vol_24h": 10466051.1348}, "\u5e01\u5b89\u4eba\u751fUSDT": {"sym": "\u5e01\u5b89\u4eba\u751fUSDT", "sl": 0, "ss": 0, "oh_score": 1, "od_score": 0, "rsi1h": 51.6, "rsi5m": 48.7, "fund": 0.005, "cvd": 0.0, "oi": 0.0, "long_pct": 39, "trend": "neutral", "ms4h": "neutral", "ms1h": "bearish", "block_long": false, "block_short": false, "btc_chg": -0.19, "final_direction": null, "final_score": 1, "price": 0.7024, "price_chg_1h": -1.1, "sq_score": 0, "ml_score": 0, "vol_24h": 10476263.03342}, "SEIUSDT": {"sym": "SEIUSDT", "sl": 0, "ss": 0, "oh_score": 0, "od_score": 0, "rsi1h": 31.3, "rsi5m": 53.5, "fund": -0.0007, "cvd": 29.6, "oi": 0.0, "long_pct": 54, "trend": "neutral", "ms4h": "neutral", "ms1h": "bearish", "block_long": false, "block_short": false, "btc_chg": -0.19, "final_direction": null, "final_score": 0, "price": 0.05196, "price_chg_1h": -2.2, "sq_score": 0, "ml_score": 0, "vol_24h": 10300281.89965}, "ALICEUSDT": {"sym": "ALICEUSDT", "sl": 0, "ss": 0, "oh_score": 0, "od_score": 0, "rsi1h": 27.9, "rsi5m": 40.3, "fund": -0.0145, "cvd": -17.6, "oi": 0.0, "long_pct": 56, "trend": "neutral", "ms4h": "neutral", "ms1h": "bearish", "block_long": false, "block_short": false, "btc_chg": -0.19, "final_direction": null, "final_score": 0, "price": 0.1238, "price_chg_1h": 2.82, "sq_score": 0, "ml_score": 0, "vol_24h": 10166897.02019}, "COHRUSDT": {"sym": "COHRUSDT", "sl": 0, "ss": 0, "oh_score": 0, "od_score": 5, "rsi1h": 24.9, "rsi5m": 49.3, "fund": 0.0, "cvd": 26.4, "oi": 0.0, "long_pct": 70, "trend": "neutral", "ms4h": "neutral", "ms1h": "bullish", "block_long": false, "block_short": false, "btc_chg": -0.19, "final_direction": null, "final_score": 5, "price": 383.0, "price_chg_1h": -4.25, "sq_score": 0, "ml_score": 0, "vol_24h": 10168439.155}, "BREVUSDT": {"sym": "BREVUSDT", "sl": 0, "ss": 0, "oh_score": 0, "od_score": 0, "rsi1h": 45.9, "rsi5m": 43.8, "fund": 0.005, "cvd": -4.6, "oi": 0.0, "long_pct": 66, "trend": "neutral", "ms4h": "neutral", "ms1h": "neutral", "block_long": false, "block_short": false, "btc_chg": -0.19, "final_direction": null, "final_score": 0, "price": 0.07979, "price_chg_1h": -10.06, "sq_score": 0, "ml_score": 0, "vol_24h": 9934135.0605}, "_ts": "12:28:20", "_btc_chg": -0.19, "_min_score": 6}